AUTHORS.md
CHANGELOG.md
LICENSE
MANIFEST.in
README.rst
setup.py
bio_pm.egg-info/PKG-INFO
bio_pm.egg-info/SOURCES.txt
bio_pm.egg-info/dependency_links.txt
bio_pm.egg-info/requires.txt
bio_pm.egg-info/top_level.txt
pm/__init__.py
pm/pattern.py
pm/status.py
tests/test_pattern.py
tests/test_pattern.pyc
tests/test_pm.py
tests/test_pm.pyc
tests/test_status.py
tests/test_status.pyc
tests/__pycache__/test_pattern.cpython-36.pyc
tests/__pycache__/test_pm.cpython-36.pyc
tests/__pycache__/test_status.cpython-36.pyc