Metadata-Version: 1.1
Name: bio-pm
Version: 0.1.1
Summary: A point mutation analyzing tool for nucleotide sequence
Home-page: https://github.com/ekeyme/bio-pm
Author: Ekeyme Mo
Author-email: ekeyme@gmail.com
License: MIT
Keywords: nucleotide mutation analyzing
Platform: UNKNOWN
Classifier: Development Status :: 4 - Beta
Classifier: Intended Audience :: Developers
Classifier: License :: OSI Approved :: MIT License
Classifier: Topic :: Scientific/Engineering :: Bio-Informatics
Classifier: Operating System :: OS Independent
Classifier: Programming Language :: Python :: 2.7
Classifier: Programming Language :: Python :: 3
Classifier: Programming Language :: Python :: 3.4
Classifier: Programming Language :: Python :: 3.5
Classifier: Programming Language :: Python :: 3 :: Only
